AUTHORS.rst
CONTRIBUTING.rst
LICENSE
MANIFEST.in
README.rst
setup.cfg
setup.py
djangocms_disqus/__init__.py
djangocms_disqus/cms_plugins.py
djangocms_disqus/compat.py
djangocms_disqus/conf.py
djangocms_disqus/exceptions.py
djangocms_disqus/middleware.py
djangocms_disqus/models.py
djangocms_disqus/utils.py
djangocms_disqus/widgets.py
djangocms_disqus.egg-info/PKG-INFO
djangocms_disqus.egg-info/SOURCES.txt
djangocms_disqus.egg-info/dependency_links.txt
djangocms_disqus.egg-info/not-zip-safe
djangocms_disqus.egg-info/requires.txt
djangocms_disqus.egg-info/top_level.txt
djangocms_disqus/migrations/0001_initial.py
djangocms_disqus/migrations/__init__.py
djangocms_disqus/south_migrations/0001_initial.py
djangocms_disqus/south_migrations/__init__.py
djangocms_disqus/static/css/djangocms_disqus/admin/djangocms_disqus.css
djangocms_disqus/static/img/djangocms_disqus/loader.gif
djangocms_disqus/static/js/djangocms_disqus/jquery.disqus.js
djangocms_disqus/static/js/djangocms_disqus/jquery.lazyload.js
djangocms_disqus/static/js/djangocms_disqus/admin/djangocms_disqus.js
djangocms_disqus/templates/djangocms_disqus/default.html
djangocms_disqus/templates/djangocms_disqus/login_success.html
djangocms_disqus/templates/djangocms_disqus/admin/shortname_widget_wrapper.html