Metadata-Version: 1.1
Name: djangocms-disqus
Version: 0.1.3
Summary: Disqus intergration for your django-cms powered site with options for Single Sign-On (SSO), lazy loading, analytics and more.
Home-page: https://github.com/mishbahr/djangocms-disqus
Author: Mishbah Razzaque
Author-email: mishbahx@gmail.com
License: BSD
Keywords: djangocms-disqus,django-cms,cmsplugin-disqus,disqus sso,lazyload
Platform: UNKNOWN
Classifier: Development Status :: 4 - Beta
Classifier: Framework :: Django
Classifier: Intended Audience :: Developers
Classifier: License :: OSI Approved :: BSD License
Classifier: Natural Language :: English
Classifier: Programming Language :: Python :: 2.7
Classifier: Programming Language :: Python :: 3
Classifier: Programming Language :: Python :: 3.3
